[
  {
    "title": "File:Coriandrum sativum 'Cilantro' kz02.jpg",
    "image_url": "https://upload.wikimedia.org/wikipedia/commons/e/e6/Coriandrum_sativum_%27Cilantro%27_kz02.jpg",
    "width": 2916,
    "height": 4082,
    "license": "CC BY-SA 4.0",
    "author": "<a href=\"//commons.wikimedia.org/wiki/User:Kenraiz\" title=\"User:Kenraiz\">Krzysztof Ziarnek, Kenraiz</a>",
    "credit": "<span class=\"int-own-work\" lang=\"en\">Own work</span>",
    "source": "Wikimedia Commons",
    "page_url": "https://commons.wikimedia.org/wiki/File:Coriandrum%20sativum%20%27Cilantro%27%20kz02.jpg"
  },
  {
    "title": "File:Coriandrum sativum 'Cilantro' kz01.jpg",
    "image_url": "https://upload.wikimedia.org/wikipedia/commons/2/29/Coriandrum_sativum_%27Cilantro%27_kz01.jpg",
    "width": 2587,
    "height": 3623,
    "license": "CC BY-SA 4.0",
    "author": "<a href=\"//commons.wikimedia.org/wiki/User:Kenraiz\" title=\"User:Kenraiz\">Krzysztof Ziarnek, Kenraiz</a>",
    "credit": "<span class=\"int-own-work\" lang=\"en\">Own work</span>",
    "source": "Wikimedia Commons",
    "page_url": "https://commons.wikimedia.org/wiki/File:Coriandrum%20sativum%20%27Cilantro%27%20kz01.jpg"
  },
  {
    "title": "File:Flor de Cilantro Mexicano.jpg",
    "image_url": "https://upload.wikimedia.org/wikipedia/commons/f/fb/Flor_de_Cilantro_Mexicano.jpg",
    "width": 4496,
    "height": 3000,
    "license": "CC BY-SA 4.0",
    "author": "<a href=\"//commons.wikimedia.org/wiki/User:Enzo_Olivo\" title=\"User:Enzo Olivo\">Armando Olivo Martín del Campo</a>",
    "credit": "<span class=\"int-own-work\" lang=\"en\">Own work</span>",
    "source": "Wikimedia Commons",
    "page_url": "https://commons.wikimedia.org/wiki/File:Flor%20de%20Cilantro%20Mexicano.jpg"
  },
  {
    "title": "File:Bumbu Rawon.jpg",
    "image_url": "https://upload.wikimedia.org/wikipedia/commons/c/c5/Bumbu_Rawon.jpg",
    "width": 5014,
    "height": 3342,
    "license": "CC BY-SA 4.0",
    "author": "<a href=\"//commons.wikimedia.org/w/index.php?title=User:Herusutimbul&amp;action=edit&amp;redlink=1\" class=\"new\" title=\"User:Herusutimbul (page does not exist)\">Herusutimbul</a>",
    "credit": "<span class=\"int-own-work\" lang=\"en\">Own work</span>",
    "source": "Wikimedia Commons",
    "page_url": "https://commons.wikimedia.org/wiki/File:Bumbu%20Rawon.jpg"
  },
  {
    "title": "File:Homemade Grown Coriandum Sativum (Cilantro).jpg",
    "image_url": "https://upload.wikimedia.org/wikipedia/commons/8/89/Homemade_Grown_Coriandum_Sativum_%28Cilantro%29.jpg",
    "width": 1173,
    "height": 1355,
    "license": "CC BY-SA 4.0",
    "author": "<a href=\"//commons.wikimedia.org/w/index.php?title=User:CuetzpalinTonatiuh&amp;action=edit&amp;redlink=1\" class=\"new\" title=\"User:CuetzpalinTonatiuh (page does not exist)\">CuetzpalinTonatiuh</a>",
    "credit": "<span class=\"int-own-work\" lang=\"en\">Own work</span>",
    "source": "Wikimedia Commons",
    "page_url": "https://commons.wikimedia.org/wiki/File:Homemade%20Grown%20Coriandum%20Sativum%20%28Cilantro%29.jpg"
  }
]